wenyan/__init__.py
wenyan-0.0.0.dist-info/WHEEL
wenyan-0.0.0.dist-info/METADATA
wenyan-0.0.0.dist-info/RECORD
