Metadata-Version: 2.1
Name: wenyan
Version: 0.0.0
Summary: Programming Language for the ancient Chinese
License: MIT
Author: Tang Ziya
Author-email: tcztzy@gmail.com
Requires-Python: >=3.9,<4.0
Classifier: License :: OSI Approved :: MIT License
Classifier: Programming Language :: Python :: 3
Classifier: Programming Language :: Python :: 3.9
